topsis_Kushagra_101917112/__init__.py
topsis_Kushagra_101917112-0.1.dist-info/METADATA
topsis_Kushagra_101917112-0.1.dist-info/WHEEL
topsis_Kushagra_101917112-0.1.dist-info/entry_points.txt
topsis_Kushagra_101917112-0.1.dist-info/license.txt
topsis_Kushagra_101917112-0.1.dist-info/top_level.txt
topsis_Kushagra_101917112-0.1.dist-info/RECORD
