Metadata-Version: 2.1
Name: topsis-Kushagra-101917112
Version: 0.1
Summary: A Python package implementing TOPSIS technique.
Author: Kushagra Rastogi
Author-email: kushagrarastogi2014@gmail.com
License: MIT
Platform: UNKNOWN
Classifier: License :: OSI Approved :: MIT License
Classifier: Programming Language :: Python :: 3
Classifier: Programming Language :: Python :: 3.9
License-File: license.txt
Requires-Dist: numpy
Requires-Dist: pandas
Requires-Dist: sys
Requires-Dist: math
